{
    "538810": {
        "success": true,
        "data": {
            "type": "game",
            "name": "Train Mechanic Simulator 2017",
            "steam_appid": 538810,
            "required_age": 0,
            "is_free": false,
            "detailed_description": "Take your opportunity as real Train Mechanic. <br />\r\nFind locomotives around game world that needs your help and repair them in one of 3 workshops localized in huge 25 km2 open world. <br />\r\nYou will be face all types of damages in all genres of trains: Diesel, Electric and even Old-School Steam units.<br />\r\n<br />\r\n- 9 trains to repair in all types: Steam, Electric and Diesel<br />\r\n- open 25 km2 world full of railways and different locations<br />\r\n- 3 workshops with more than 1000 parts to repair<br />\r\n- unique Economy System – you will decide about strategy of repair and ROI of it",
            "about_the_game": "Take your opportunity as real Train Mechanic. <br />\r\nFind locomotives around game world that needs your help and repair them in one of 3 workshops localized in huge 25 km2 open world. <br />\r\nYou will be face all types of damages in all genres of trains: Diesel, Electric and even Old-School Steam units.<br />\r\n<br />\r\n- 9 trains to repair in all types: Steam, Electric and Diesel<br />\r\n- open 25 km2 world full of railways and different locations<br />\r\n- 3 workshops with more than 1000 parts to repair<br />\r\n- unique Economy System – you will decide about strategy of repair and ROI of it",
            "short_description": "Take your opportunity as real Train Mechanic. Find locomotives around game world that needs your help and repair them in one of 3 workshops localized in huge 25 km2 open world. You will be face all types of damages in all genres of trains: Diesel, Electric and even Old-School Steam units.",
            "supported_languages": "English, French, Italian, German, Spanish - Spain, Polish, Russian, Czech, Hungarian",
            "header_image": "https://steamcdn-a.akamaihd.net/steam/apps/538810/header.jpg?t=1542458638",
            "website": null,
            "pc_requirements": {
                "minimum": "<strong>Minimum:</strong><br><ul class=\"bb_ul\"><li><strong>OS:</strong> Windows 7<br></li><li><strong>Processor:</strong> Pentium Core 2 Duo<br></li><li><strong>Memory:</strong> 4 GB RAM<br></li><li><strong>Graphics:</strong> Geforce GT560<br></li><li><strong>DirectX:</strong> Version 11<br></li><li><strong>Storage:</strong> 5 GB available space</li></ul>",
                "recommended": "<strong>Recommended:</strong><br><ul class=\"bb_ul\"><li><strong>OS:</strong> Windows 8, 10<br></li><li><strong>Processor:</strong> Pentium Core Quad<br></li><li><strong>Memory:</strong> 8 GB RAM<br></li><li><strong>Graphics:</strong> Geforce GT950 or better<br></li><li><strong>DirectX:</strong> Version 12<br></li><li><strong>Storage:</strong> 5 GB available space</li></ul>"
            },
            "mac_requirements": [],
            "linux_requirements": [],
            "developers": [
                "Si7 Studio"
            ],
            "publishers": [
                "Si7 Studio"
            ],
            "price_overview": {
                "currency": "EUR",
                "initial": 1499,
                "final": 1499,
                "discount_percent": 0,
                "initial_formatted": "",
                "final_formatted": "14,99€"
            },
            "packages": [
                131741
            ],
            "package_groups": [
                {
                    "name": "default",
                    "title": "Buy Train Mechanic Simulator 2017",
                    "description": "",
                    "selection_text": "Select a purchase option",
                    "save_text": "",
                    "display_type": 0,
                    "is_recurring_subscription": "false",
                    "subs": [
                        {
                            "packageid": 131741,
                            "percent_savings_text": "",
                            "percent_savings": 0,
                            "option_text": "Train Mechanic Simulator 2017 - 14,99€",
                            "option_description": "",
                            "can_get_free_license": "0",
                            "is_free_license": false,
                            "price_in_cents_with_discount": 1499
                        }
                    ]
                }
            ],
            "platforms": {
                "windows": true,
                "mac": false,
                "linux": false
            },
            "categories": [
                {
                    "id": 2,
                    "description": "Single-player"
                }
            ],
            "genres": [
                {
                    "id": "28",
                    "description": "Simulation"
                }
            ],
            "screenshots": [
                {
                    "id": 0,
                    "path_thumbnail": "https://steamcdn-a.akamaihd.net/steam/apps/538810/ss_4f833ac3e8675dfad52585ff994e6a3f29452033.600x338.jpg?t=1542458638",
                    "path_full": "https://steamcdn-a.akamaihd.net/steam/apps/538810/ss_4f833ac3e8675dfad52585ff994e6a3f29452033.1920x1080.jpg?t=1542458638"
                },
                {
                    "id": 1,
                    "path_thumbnail": "https://steamcdn-a.akamaihd.net/steam/apps/538810/ss_0de443116f8ca32ab5a7b8285a30912b96168581.600x338.jpg?t=1542458638",
                    "path_full": "https://steamcdn-a.akamaihd.net/steam/apps/538810/ss_0de443116f8ca32ab5a7b8285a30912b96168581.1920x1080.jpg?t=1542458638"
                },
                {
                    "id": 2,
                    "path_thumbnail": "https://steamcdn-a.akamaihd.net/steam/apps/538810/ss_5cc38a5449b11beb985514826945ff01745c5f9e.600x338.jpg?t=1542458638",
                    "path_full": "https://steamcdn-a.akamaihd.net/steam/apps/538810/ss_5cc38a5449b11beb985514826945ff01745c5f9e.1920x1080.jpg?t=1542458638"
                },
                {
                    "id": 3,
                    "path_thumbnail": "https://steamcdn-a.akamaihd.net/steam/apps/538810/ss_d3dec5f122bff03de006cc2521be4e7d41359294.600x338.jpg?t=1542458638",
                    "path_full": "https://steamcdn-a.akamaihd.net/steam/apps/538810/ss_d3dec5f122bff03de006cc2521be4e7d41359294.1920x1080.jpg?t=1542458638"
                },
                {
                    "id": 4,
                    "path_thumbnail": "https://steamcdn-a.akamaihd.net/steam/apps/538810/ss_9d10db22be64bc2be38b45211faf2296053ca2c5.600x338.jpg?t=1542458638",
                    "path_full": "https://steamcdn-a.akamaihd.net/steam/apps/538810/ss_9d10db22be64bc2be38b45211faf2296053ca2c5.1920x1080.jpg?t=1542458638"
                },
                {
                    "id": 5,
                    "path_thumbnail": "https://steamcdn-a.akamaihd.net/steam/apps/538810/ss_a234b7f27968a440d77dc2077c04eced6c4b3f4e.600x338.jpg?t=1542458638",
                    "path_full": "https://steamcdn-a.akamaihd.net/steam/apps/538810/ss_a234b7f27968a440d77dc2077c04eced6c4b3f4e.1920x1080.jpg?t=1542458638"
                },
                {
                    "id": 6,
                    "path_thumbnail": "https://steamcdn-a.akamaihd.net/steam/apps/538810/ss_0c8ec2449ea5e1ec3546b637bd587ae9a9dde5c9.600x338.jpg?t=1542458638",
                    "path_full": "https://steamcdn-a.akamaihd.net/steam/apps/538810/ss_0c8ec2449ea5e1ec3546b637bd587ae9a9dde5c9.1920x1080.jpg?t=1542458638"
                },
                {
                    "id": 7,
                    "path_thumbnail": "https://steamcdn-a.akamaihd.net/steam/apps/538810/ss_cdb5cc990e225cc92f41d132ef63d727f07e5784.600x338.jpg?t=1542458638",
                    "path_full": "https://steamcdn-a.akamaihd.net/steam/apps/538810/ss_cdb5cc990e225cc92f41d132ef63d727f07e5784.1920x1080.jpg?t=1542458638"
                },
                {
                    "id": 8,
                    "path_thumbnail": "https://steamcdn-a.akamaihd.net/steam/apps/538810/ss_e322dfbee590ccb7872e49f584ab28b450794a69.600x338.jpg?t=1542458638",
                    "path_full": "https://steamcdn-a.akamaihd.net/steam/apps/538810/ss_e322dfbee590ccb7872e49f584ab28b450794a69.1920x1080.jpg?t=1542458638"
                },
                {
                    "id": 9,
                    "path_thumbnail": "https://steamcdn-a.akamaihd.net/steam/apps/538810/ss_e143291e71f2f0763e12c8281e5378da06298449.600x338.jpg?t=1542458638",
                    "path_full": "https://steamcdn-a.akamaihd.net/steam/apps/538810/ss_e143291e71f2f0763e12c8281e5378da06298449.1920x1080.jpg?t=1542458638"
                },
                {
                    "id": 10,
                    "path_thumbnail": "https://steamcdn-a.akamaihd.net/steam/apps/538810/ss_636c04232ad3b376efab3ac08e4a51a5aede4826.600x338.jpg?t=1542458638",
                    "path_full": "https://steamcdn-a.akamaihd.net/steam/apps/538810/ss_636c04232ad3b376efab3ac08e4a51a5aede4826.1920x1080.jpg?t=1542458638"
                },
                {
                    "id": 11,
                    "path_thumbnail": "https://steamcdn-a.akamaihd.net/steam/apps/538810/ss_bc65bd33b567639c02913f76bffda9065f9890d8.600x338.jpg?t=1542458638",
                    "path_full": "https://steamcdn-a.akamaihd.net/steam/apps/538810/ss_bc65bd33b567639c02913f76bffda9065f9890d8.1920x1080.jpg?t=1542458638"
                },
                {
                    "id": 12,
                    "path_thumbnail": "https://steamcdn-a.akamaihd.net/steam/apps/538810/ss_45a7917a1241b13790bc1d37bc60cf2fbf5a49ed.600x338.jpg?t=1542458638",
                    "path_full": "https://steamcdn-a.akamaihd.net/steam/apps/538810/ss_45a7917a1241b13790bc1d37bc60cf2fbf5a49ed.1920x1080.jpg?t=1542458638"
                },
                {
                    "id": 13,
                    "path_thumbnail": "https://steamcdn-a.akamaihd.net/steam/apps/538810/ss_6e38c8ee9f5a85b666d86a1d17f8bc3a7a9f9ee0.600x338.jpg?t=1542458638",
                    "path_full": "https://steamcdn-a.akamaihd.net/steam/apps/538810/ss_6e38c8ee9f5a85b666d86a1d17f8bc3a7a9f9ee0.1920x1080.jpg?t=1542458638"
                },
                {
                    "id": 14,
                    "path_thumbnail": "https://steamcdn-a.akamaihd.net/steam/apps/538810/ss_acc0930bb641311e2b14cbba25570207ab064714.600x338.jpg?t=1542458638",
                    "path_full": "https://steamcdn-a.akamaihd.net/steam/apps/538810/ss_acc0930bb641311e2b14cbba25570207ab064714.1920x1080.jpg?t=1542458638"
                },
                {
                    "id": 15,
                    "path_thumbnail": "https://steamcdn-a.akamaihd.net/steam/apps/538810/ss_4c0a20a7b063fc8d2e92e8de3d3138295babd11f.600x338.jpg?t=1542458638",
                    "path_full": "https://steamcdn-a.akamaihd.net/steam/apps/538810/ss_4c0a20a7b063fc8d2e92e8de3d3138295babd11f.1920x1080.jpg?t=1542458638"
                },
                {
                    "id": 16,
                    "path_thumbnail": "https://steamcdn-a.akamaihd.net/steam/apps/538810/ss_461f8a3b2a75ddd9480f9532dc4c9cf3bb6ca1ad.600x338.jpg?t=1542458638",
                    "path_full": "https://steamcdn-a.akamaihd.net/steam/apps/538810/ss_461f8a3b2a75ddd9480f9532dc4c9cf3bb6ca1ad.1920x1080.jpg?t=1542458638"
                },
                {
                    "id": 17,
                    "path_thumbnail": "https://steamcdn-a.akamaihd.net/steam/apps/538810/ss_48054b904dc93b522c3925c613170a414b093f99.600x338.jpg?t=1542458638",
                    "path_full": "https://steamcdn-a.akamaihd.net/steam/apps/538810/ss_48054b904dc93b522c3925c613170a414b093f99.1920x1080.jpg?t=1542458638"
                },
                {
                    "id": 18,
                    "path_thumbnail": "https://steamcdn-a.akamaihd.net/steam/apps/538810/ss_58a3d8bbceab4420fa9bb9ef27311b34666087c5.600x338.jpg?t=1542458638",
                    "path_full": "https://steamcdn-a.akamaihd.net/steam/apps/538810/ss_58a3d8bbceab4420fa9bb9ef27311b34666087c5.1920x1080.jpg?t=1542458638"
                },
                {
                    "id": 19,
                    "path_thumbnail": "https://steamcdn-a.akamaihd.net/steam/apps/538810/ss_fccc477e615a62860a90d3049fd943c5f33f2ebb.600x338.jpg?t=1542458638",
                    "path_full": "https://steamcdn-a.akamaihd.net/steam/apps/538810/ss_fccc477e615a62860a90d3049fd943c5f33f2ebb.1920x1080.jpg?t=1542458638"
                }
            ],
            "movies": [
                {
                    "id": 256681829,
                    "name": "maintrailer",
                    "thumbnail": "https://steamcdn-a.akamaihd.net/steam/apps/256681829/movie.293x165.jpg?t=1490282062",
                    "webm": {
                        "480": "http://steamcdn-a.akamaihd.net/steam/apps/256681829/movie480.webm?t=1490282062",
                        "max": "http://steamcdn-a.akamaihd.net/steam/apps/256681829/movie_max.webm?t=1490282062"
                    },
                    "highlight": true
                }
            ],
            "recommendations": {
                "total": 264
            },
            "achievements": {
                "total": 0
            },
            "release_date": {
                "coming_soon": false,
                "date": "23 Mar, 2017"
            },
            "support_info": {
                "url": "www.playway.com",
                "email": "contact@playway.com"
            },
            "background": "https://steamcdn-a.akamaihd.net/steam/apps/538810/page_bg_generated_v6b.jpg?t=1542458638",
            "content_descriptors": {
                "ids": [],
                "notes": null
            }
        }
    }
}