{
    "706690": {
        "success": true,
        "data": {
            "type": "game",
            "name": "Megatronic Void",
            "steam_appid": 706690,
            "required_age": 0,
            "is_free": false,
            "controller_support": "full",
            "detailed_description": "The legendary 80s. in Megatronic Void you are dressed in a scientist, the earth has been devastated by a nuclear explosion, your job is to conquer and explore Megatron, recover alien artifacts to free Megatron zones. Humanity must leave the planet earth and only you can free them. But first you have to defeat the alien race on Megatron.<br />\r\n<br />\r\nKey Features:<br />\r\n<br />\r\n* locates the megatron guards and retrieves the gears to build the generator<br />\r\n<br />\r\n* Retrieve alien artifacts to free Megatron<br />\r\n<br />\r\n* Absorb the alien energy to boost your weapon<br />\r\n<br />\r\n* Save mankind<br />\r\n<br />\r\n* Live the 80s with the simulation of c64 loading tribute.<br />\r\n<br />\r\n* faithful reconstruction of a 80s tv monitor",
            "about_the_game": "The legendary 80s. in Megatronic Void you are dressed in a scientist, the earth has been devastated by a nuclear explosion, your job is to conquer and explore Megatron, recover alien artifacts to free Megatron zones. Humanity must leave the planet earth and only you can free them. But first you have to defeat the alien race on Megatron.<br />\r\n<br />\r\nKey Features:<br />\r\n<br />\r\n* locates the megatron guards and retrieves the gears to build the generator<br />\r\n<br />\r\n* Retrieve alien artifacts to free Megatron<br />\r\n<br />\r\n* Absorb the alien energy to boost your weapon<br />\r\n<br />\r\n* Save mankind<br />\r\n<br />\r\n* Live the 80s with the simulation of c64 loading tribute.<br />\r\n<br />\r\n* faithful reconstruction of a 80s tv monitor",
            "short_description": "The legendary 80s. in Megatronic Void you are dressed in a scientist, the earth has been devastated by a nuclear explosion, your job is to conquer and explore Megatron, recover alien artifacts to free Megatron zones.",
            "supported_languages": "English",
            "header_image": "https://steamcdn-a.akamaihd.net/steam/apps/706690/header.jpg?t=1505893847",
            "website": "https://www.facebook.com/megatronicvoid/",
            "pc_requirements": {
                "minimum": "<strong>Minimum:</strong><br><ul class=\"bb_ul\"><li><strong>OS:</strong> Microsoft Windows 7,8,10<br></li><li><strong>Processor:</strong> Cpu dual core 2,5 Ghz or higher<br></li><li><strong>Memory:</strong> 2 GB RAM<br></li><li><strong>Graphics:</strong> intel Hd 4000 \\ ati series 7000 or higher<br></li><li><strong>DirectX:</strong> Version 9.0c<br></li><li><strong>Storage:</strong> 500 MB available space<br></li><li><strong>Sound Card:</strong> Common sound card</li></ul>",
                "recommended": "<strong>Recommended:</strong><br><ul class=\"bb_ul\"><li><strong>OS:</strong> Microsoft Windows 7,8,10<br></li><li><strong>Processor:</strong> Cpu dual core 2,5 Ghz or higher<br></li><li><strong>Memory:</strong> 2 GB RAM<br></li><li><strong>Graphics:</strong> nvidia geforce 650 \\ ati series 7770 or higher<br></li><li><strong>DirectX:</strong> Version 9.0c<br></li><li><strong>Storage:</strong> 500 MB available space<br></li><li><strong>Sound Card:</strong> Common sound card</li></ul>"
            },
            "mac_requirements": [],
            "linux_requirements": [],
            "developers": [
                "Firestorm Entertainment"
            ],
            "publishers": [
                "Firestorm Entertainment"
            ],
            "price_overview": {
                "currency": "EUR",
                "initial": 399,
                "final": 399,
                "discount_percent": 0,
                "initial_formatted": "",
                "final_formatted": "3,99€"
            },
            "packages": [
                203990
            ],
            "package_groups": [
                {
                    "name": "default",
                    "title": "Buy Megatronic Void",
                    "description": "",
                    "selection_text": "Select a purchase option",
                    "save_text": "",
                    "display_type": 0,
                    "is_recurring_subscription": "false",
                    "subs": [
                        {
                            "packageid": 203990,
                            "percent_savings_text": "",
                            "percent_savings": 0,
                            "option_text": "Megatronic Void - 3,99€",
                            "option_description": "",
                            "can_get_free_license": "0",
                            "is_free_license": false,
                            "price_in_cents_with_discount": 399
                        }
                    ]
                }
            ],
            "platforms": {
                "windows": true,
                "mac": false,
                "linux": false
            },
            "categories": [
                {
                    "id": 2,
                    "description": "Single-player"
                },
                {
                    "id": 28,
                    "description": "Full controller support"
                }
            ],
            "genres": [
                {
                    "id": "1",
                    "description": "Action"
                },
                {
                    "id": "23",
                    "description": "Indie"
                }
            ],
            "screenshots": [
                {
                    "id": 0,
                    "path_thumbnail": "https://steamcdn-a.akamaihd.net/steam/apps/706690/ss_34e8a20dd17a399bf655f4c8f2fc9739363c788e.600x338.jpg?t=1505893847",
                    "path_full": "https://steamcdn-a.akamaihd.net/steam/apps/706690/ss_34e8a20dd17a399bf655f4c8f2fc9739363c788e.1920x1080.jpg?t=1505893847"
                },
                {
                    "id": 1,
                    "path_thumbnail": "https://steamcdn-a.akamaihd.net/steam/apps/706690/ss_d46805f2074d0acded0d60ea20d310f69ce8c7e5.600x338.jpg?t=1505893847",
                    "path_full": "https://steamcdn-a.akamaihd.net/steam/apps/706690/ss_d46805f2074d0acded0d60ea20d310f69ce8c7e5.1920x1080.jpg?t=1505893847"
                },
                {
                    "id": 2,
                    "path_thumbnail": "https://steamcdn-a.akamaihd.net/steam/apps/706690/ss_a7d2dd551163295509e4fa84224be2c2c0e8cfc0.600x338.jpg?t=1505893847",
                    "path_full": "https://steamcdn-a.akamaihd.net/steam/apps/706690/ss_a7d2dd551163295509e4fa84224be2c2c0e8cfc0.1920x1080.jpg?t=1505893847"
                },
                {
                    "id": 3,
                    "path_thumbnail": "https://steamcdn-a.akamaihd.net/steam/apps/706690/ss_a660853e6f9d36c7cce6daa54570692038050d2b.600x338.jpg?t=1505893847",
                    "path_full": "https://steamcdn-a.akamaihd.net/steam/apps/706690/ss_a660853e6f9d36c7cce6daa54570692038050d2b.1920x1080.jpg?t=1505893847"
                },
                {
                    "id": 4,
                    "path_thumbnail": "https://steamcdn-a.akamaihd.net/steam/apps/706690/ss_7de274bc295a2f5ad927f26e3f6fda724d150be4.600x338.jpg?t=1505893847",
                    "path_full": "https://steamcdn-a.akamaihd.net/steam/apps/706690/ss_7de274bc295a2f5ad927f26e3f6fda724d150be4.1920x1080.jpg?t=1505893847"
                }
            ],
            "movies": [
                {
                    "id": 256693992,
                    "name": "Megatronic Void",
                    "thumbnail": "https://steamcdn-a.akamaihd.net/steam/apps/256693992/movie.293x165.jpg?t=1504735664",
                    "webm": {
                        "480": "http://steamcdn-a.akamaihd.net/steam/apps/256693992/movie480.webm?t=1504735664",
                        "max": "http://steamcdn-a.akamaihd.net/steam/apps/256693992/movie_max.webm?t=1504735664"
                    },
                    "highlight": true
                }
            ],
            "achievements": {
                "total": 0
            },
            "release_date": {
                "coming_soon": false,
                "date": "20 Sep, 2017"
            },
            "support_info": {
                "url": "https://www.facebook.com/megatronicvoid/",
                "email": ""
            },
            "background": "https://steamcdn-a.akamaihd.net/steam/apps/706690/page_bg_generated_v6b.jpg?t=1505893847",
            "content_descriptors": {
                "ids": [],
                "notes": null
            }
        }
    }
}