{
    "774071": {
        "success": true,
        "data": {
            "type": "dlc",
            "name": "NEKOPARA OVA Set",
            "steam_appid": 774071,
            "required_age": 0,
            "is_free": false,
            "detailed_description": "<strong>NEKOPARA OVA Set</strong><br><br>This special DLC set contains both the NEKOPARA Chronicle Artbook and the NEKOPARA OVA Soundtrack<br><br><strong>NEKOPARA Chronicle Artbook</strong><br><br>This artbook contains the collected illustrated works from the NekoPara series. Spanning 10 years from 2008 to 2017, see how Chocola, Vanilla and the other catgirls of NekoPara have evolved into the lovable catgirls we see now!<br><br>Details<br><ul class=\"bb_ul\"><li>Length: 210 Pages<br></li><li>Includes a list of backers who supported the NEKOPARA OVA Kickstarter Campaign<br><br><strong>NEKOPARA OVA Soundtrack</strong><br><br>The soundtrack features the music from the NEKOPARA OVA including the opening and ending songs.<br><br>Details<br></li><li>Contains 26 tracks<br></li><li>Opening Theme: Baby→Lady LOVE (Performed by Ray)<br></li><li>Ending Theme: ▲MEW▲△MEW△CAKE (Performed byKOTOKO)<br></li><li>FLAC format</li></ul>",
            "about_the_game": "<strong>NEKOPARA OVA Set</strong><br><br>This special DLC set contains both the NEKOPARA Chronicle Artbook and the NEKOPARA OVA Soundtrack<br><br><strong>NEKOPARA Chronicle Artbook</strong><br><br>This artbook contains the collected illustrated works from the NekoPara series. Spanning 10 years from 2008 to 2017, see how Chocola, Vanilla and the other catgirls of NekoPara have evolved into the lovable catgirls we see now!<br><br>Details<br><ul class=\"bb_ul\"><li>Length: 210 Pages<br></li><li>Includes a list of backers who supported the NEKOPARA OVA Kickstarter Campaign<br><br><strong>NEKOPARA OVA Soundtrack</strong><br><br>The soundtrack features the music from the NEKOPARA OVA including the opening and ending songs.<br><br>Details<br></li><li>Contains 26 tracks<br></li><li>Opening Theme: Baby→Lady LOVE (Performed by Ray)<br></li><li>Ending Theme: ▲MEW▲△MEW△CAKE (Performed byKOTOKO)<br></li><li>FLAC format</li></ul>",
            "short_description": "This special DLC set contains both the NEKOPARA Chronicle Artbook and the NEKOPARA OVA Soundtrack",
            "fullgame": {
                "appid": "333600",
                "name": "NEKOPARA Vol. 1"
            },
            "supported_languages": "English, Japanese<strong>*</strong>, Traditional Chinese<br><strong>*</strong>languages with full audio support",
            "header_image": "https://steamcdn-a.akamaihd.net/steam/apps/774071/header.jpg?t=1515477021",
            "website": "http://nekoparaova.com/",
            "pc_requirements": {
                "minimum": "<strong>Minimum:</strong><br><ul class=\"bb_ul\"><li><strong>Graphics:</strong> DirectX® 9 Compatible Graphics Card<br></li><li><strong>Storage:</strong> 520 MB available space<br></li><li><strong>Sound Card:</strong> FLAC decoder required</li></ul>"
            },
            "mac_requirements": {
                "minimum": "<strong>Minimum:</strong><br><ul class=\"bb_ul\"><li><strong>Graphics:</strong> OpenGL compatible card<br></li><li><strong>Storage:</strong> 520 MB available space<br></li><li><strong>Sound Card:</strong> FLAC decoder required</li></ul>"
            },
            "linux_requirements": {
                "minimum": "<strong>Minimum:</strong><br><ul class=\"bb_ul\"><li><strong>Graphics:</strong> OpenGL compatible card<br></li><li><strong>Storage:</strong> 520 MB available space<br></li><li><strong>Sound Card:</strong> FLAC decoder required</li></ul>"
            },
            "legal_notice": "<i>Distributed on Steam, under license, by Sekai Project, on behalf of NEKO WORKs</i>",
            "developers": [
                "NEKO WORKs"
            ],
            "publishers": [
                "Sekai Project",
                "NEKO WORKs"
            ],
            "price_overview": {
                "currency": "EUR",
                "initial": 2799,
                "final": 2799,
                "discount_percent": 0,
                "initial_formatted": "",
                "final_formatted": "27,99€"
            },
            "packages": [
                231986
            ],
            "package_groups": [
                {
                    "name": "default",
                    "title": "Buy NEKOPARA OVA Set",
                    "description": "",
                    "selection_text": "Select a purchase option",
                    "save_text": "",
                    "display_type": 0,
                    "is_recurring_subscription": "false",
                    "subs": [
                        {
                            "packageid": 231986,
                            "percent_savings_text": "",
                            "percent_savings": 0,
                            "option_text": "NEKOPARA OVA Set - 27,99€",
                            "option_description": "",
                            "can_get_free_license": "0",
                            "is_free_license": false,
                            "price_in_cents_with_discount": 2799
                        }
                    ]
                }
            ],
            "platforms": {
                "windows": true,
                "mac": true,
                "linux": true
            },
            "categories": [
                {
                    "id": 2,
                    "description": "Single-player"
                },
                {
                    "id": 21,
                    "description": "Downloadable Content"
                }
            ],
            "genres": [
                {
                    "id": "71",
                    "description": "Sexual Content"
                },
                {
                    "id": "72",
                    "description": "Nudity"
                },
                {
                    "id": "4",
                    "description": "Casual"
                },
                {
                    "id": "23",
                    "description": "Indie"
                }
            ],
            "screenshots": [
                {
                    "id": 0,
                    "path_thumbnail": "https://steamcdn-a.akamaihd.net/steam/apps/774071/ss_bda64666d87e8f3e13b12c1a8edc57e7c3fcd43c.600x338.jpg?t=1515477021",
                    "path_full": "https://steamcdn-a.akamaihd.net/steam/apps/774071/ss_bda64666d87e8f3e13b12c1a8edc57e7c3fcd43c.1920x1080.jpg?t=1515477021"
                },
                {
                    "id": 1,
                    "path_thumbnail": "https://steamcdn-a.akamaihd.net/steam/apps/774071/ss_baee95949aef645a02cc223499ddbc50a09243fa.600x338.jpg?t=1515477021",
                    "path_full": "https://steamcdn-a.akamaihd.net/steam/apps/774071/ss_baee95949aef645a02cc223499ddbc50a09243fa.1920x1080.jpg?t=1515477021"
                },
                {
                    "id": 2,
                    "path_thumbnail": "https://steamcdn-a.akamaihd.net/steam/apps/774071/ss_eab0e2cfb22a1c20fc559e4c21add8129d1a7b22.600x338.jpg?t=1515477021",
                    "path_full": "https://steamcdn-a.akamaihd.net/steam/apps/774071/ss_eab0e2cfb22a1c20fc559e4c21add8129d1a7b22.1920x1080.jpg?t=1515477021"
                }
            ],
            "achievements": {
                "total": 0
            },
            "release_date": {
                "coming_soon": false,
                "date": "8 Jan, 2018"
            },
            "support_info": {
                "url": "https://sekaiproject.com/contact/",
                "email": ""
            },
            "background": "https://steamcdn-a.akamaihd.net/steam/apps/774071/page_bg_generated_v6b.jpg?t=1515477021",
            "content_descriptors": {
                "ids": [
                    1,
                    5
                ],
                "notes": null
            }
        }
    }
}