{
    "879930": {
        "success": true,
        "data": {
            "type": "video",
            "name": "Proxima B Music Video - Dalziel X Capon Design",
            "steam_appid": 879930,
            "required_age": 0,
            "is_free": false,
            "controller_support": "full",
            "detailed_description": "<h1>Steam 360 Video Beta</h1><p>This video is part of the Steam 360 Video beta program. After installing the Steam 360 Video tool in the Steam Client, you can watch this video in a supported Virtual Reality headset or on your desktop monitor. More information can be found in the <a href=\"https://support.steampowered.com/kb_article.php?ref=8699-OASD-1871#360\">Steam 360 Video FAQ</a>.</p><br><h1>About the Video</h1>Tokyo based EDM artist Dalziel and Pacific Northwest VR director Capon Design have teamed up to bring you this music video titled Proxima B. Step into an experimental cyberpunk dream experience and let the music take you on a ride.",
            "about_the_game": "Tokyo based EDM artist Dalziel and Pacific Northwest VR director Capon Design have teamed up to bring you this music video titled Proxima B. Step into an experimental cyberpunk dream experience and let the music take you on a ride.",
            "short_description": "Tokyo based EDM artist Dalziel and Pacific Northwest VR director Capon Design have teamed up to bring you this music video titled Proxima B. Step into an experimental cyberpunk dream experience and let the music take you on a ride.",
            "fullgame": {
                "appid": null,
                "name": "Uninitialized"
            },
            "header_image": "https://steamcdn-a.akamaihd.net/steam/apps/879930/header.jpg?t=1531259811",
            "website": "http://www.studiocapon.com/",
            "pc_requirements": {
                "minimum": "<strong>Minimum:</strong><br><ul class=\"bb_ul\"><li><strong>OS:</strong> Windows 10, 64-Bit Only<br></li><li><strong>Processor:</strong> Intel® i5-4590, AMD FX 8350 equivalent or better<br></li><li><strong>Memory:</strong> 4 GB RAM<br></li><li><strong>Graphics:</strong> NVIDIA GeForce® GTX 970, AMD Radeon™ R9 290 equivalent or better<br></li><li><strong>Network:</strong> Broadband Internet connection<br></li><li><strong>Storage:</strong> 50 MB available space<br></li><li><strong>Additional Notes:</strong> Bandwidth requirements depend on the resolution and quality of the video being played. Please see the <a href=\"https://support.steampowered.com/kb_article.php?ref=8699-OASD-1871#360_bandwidth\" target=\"_blank\" rel=\"noreferrer\"  >Steam 360 Video FAQ</a> for more information.</li></ul>"
            },
            "mac_requirements": {
                "minimum": "<strong>Minimum:</strong><br><ul class=\"bb_ul\"><li><strong>OS:</strong> Windows 10, 64-Bit Only<br></li><li><strong>Processor:</strong> Intel® i5-4590, AMD FX 8350 equivalent or better<br></li><li><strong>Memory:</strong> 4 GB RAM<br></li><li><strong>Graphics:</strong> NVIDIA GeForce® GTX 970, AMD Radeon™ R9 290 equivalent or better<br></li><li><strong>Network:</strong> Broadband Internet connection<br></li><li><strong>Storage:</strong> 50 MB available space<br></li><li><strong>Additional Notes:</strong> Bandwidth requirements depend on the resolution and quality of the video being played. Please see the <a href=\"https://support.steampowered.com/kb_article.php?ref=8699-OASD-1871#360_bandwidth\" target=\"_blank\" rel=\"noreferrer\"  >Steam 360 Video FAQ</a> for more information.</li></ul>"
            },
            "linux_requirements": {
                "minimum": "<strong>Minimum:</strong><br><ul class=\"bb_ul\"><li><strong>OS:</strong> Windows 10, 64-Bit Only<br></li><li><strong>Processor:</strong> Intel® i5-4590, AMD FX 8350 equivalent or better<br></li><li><strong>Memory:</strong> 4 GB RAM<br></li><li><strong>Graphics:</strong> NVIDIA GeForce® GTX 970, AMD Radeon™ R9 290 equivalent or better<br></li><li><strong>Network:</strong> Broadband Internet connection<br></li><li><strong>Storage:</strong> 50 MB available space<br></li><li><strong>Additional Notes:</strong> Bandwidth requirements depend on the resolution and quality of the video being played. Please see the <a href=\"https://support.steampowered.com/kb_article.php?ref=8699-OASD-1871#360_bandwidth\" target=\"_blank\" rel=\"noreferrer\"  >Steam 360 Video FAQ</a> for more information.</li></ul>"
            },
            "developers": [
                "Studio Capon, LLC"
            ],
            "publishers": [
                "Studio Capon, LLC"
            ],
            "price_overview": {
                "currency": "EUR",
                "initial": 79,
                "final": 79,
                "discount_percent": 0,
                "initial_formatted": "",
                "final_formatted": "0,79€"
            },
            "packages": [
                278888,
                278887
            ],
            "package_groups": [
                {
                    "name": "default",
                    "title": "Buy Proxima B Music Video - Dalziel X Capon Design",
                    "description": "",
                    "selection_text": "Select a purchase option",
                    "save_text": "",
                    "display_type": 0,
                    "is_recurring_subscription": "false",
                    "subs": [
                        {
                            "packageid": 278888,
                            "percent_savings_text": "",
                            "percent_savings": 0,
                            "option_text": "Proxima B - 0,79€",
                            "option_description": "",
                            "can_get_free_license": "0",
                            "is_free_license": false,
                            "price_in_cents_with_discount": 79
                        },
                        {
                            "packageid": 278887,
                            "percent_savings_text": "",
                            "percent_savings": 0,
                            "option_text": "Proxima B - 1,59€",
                            "option_description": "",
                            "can_get_free_license": "0",
                            "is_free_license": false,
                            "price_in_cents_with_discount": 159
                        }
                    ]
                }
            ],
            "platforms": {
                "windows": true,
                "mac": false,
                "linux": false
            },
            "categories": [
                {
                    "id": 28,
                    "description": "Full controller support"
                },
                {
                    "id": 33,
                    "description": "Native Steam Controller Support"
                }
            ],
            "genres": [
                {
                    "id": "85",
                    "description": "360 Video"
                }
            ],
            "screenshots": [
                {
                    "id": 0,
                    "path_thumbnail": "https://steamcdn-a.akamaihd.net/steam/apps/879930/ss_a0f30918c5383ff2f29cdee42dcaa4f06f041e31.600x338.jpg?t=1531259811",
                    "path_full": "https://steamcdn-a.akamaihd.net/steam/apps/879930/ss_a0f30918c5383ff2f29cdee42dcaa4f06f041e31.1920x1080.jpg?t=1531259811"
                },
                {
                    "id": 1,
                    "path_thumbnail": "https://steamcdn-a.akamaihd.net/steam/apps/879930/ss_3e32af0e389843c2074797743ddce5bef8da2474.600x338.jpg?t=1531259811",
                    "path_full": "https://steamcdn-a.akamaihd.net/steam/apps/879930/ss_3e32af0e389843c2074797743ddce5bef8da2474.1920x1080.jpg?t=1531259811"
                },
                {
                    "id": 2,
                    "path_thumbnail": "https://steamcdn-a.akamaihd.net/steam/apps/879930/ss_e2df4d345b698e2491d46ad3a0d2739f6789fc77.600x338.jpg?t=1531259811",
                    "path_full": "https://steamcdn-a.akamaihd.net/steam/apps/879930/ss_e2df4d345b698e2491d46ad3a0d2739f6789fc77.1920x1080.jpg?t=1531259811"
                },
                {
                    "id": 3,
                    "path_thumbnail": "https://steamcdn-a.akamaihd.net/steam/apps/879930/ss_402fe1ac965347480acc325699508a284cd1b911.600x338.jpg?t=1531259811",
                    "path_full": "https://steamcdn-a.akamaihd.net/steam/apps/879930/ss_402fe1ac965347480acc325699508a284cd1b911.1920x1080.jpg?t=1531259811"
                },
                {
                    "id": 4,
                    "path_thumbnail": "https://steamcdn-a.akamaihd.net/steam/apps/879930/ss_9e41445ad583f59183c4dd5c715c77f50e63be88.600x338.jpg?t=1531259811",
                    "path_full": "https://steamcdn-a.akamaihd.net/steam/apps/879930/ss_9e41445ad583f59183c4dd5c715c77f50e63be88.1920x1080.jpg?t=1531259811"
                }
            ],
            "movies": [
                {
                    "id": 256719155,
                    "name": "Proxima B Trailer",
                    "thumbnail": "https://steamcdn-a.akamaihd.net/steam/apps/256719155/movie.293x165.jpg?t=1530427331",
                    "webm": {
                        "480": "http://steamcdn-a.akamaihd.net/steam/apps/256719155/movie480.webm?t=1530427331",
                        "max": "http://steamcdn-a.akamaihd.net/steam/apps/256719155/movie_max.webm?t=1530427331"
                    },
                    "highlight": true
                }
            ],
            "release_date": {
                "coming_soon": false,
                "date": "10 Jul, 2018"
            },
            "support_info": {
                "url": "",
                "email": "manager@studiocapon.com"
            },
            "background": "https://steamcdn-a.akamaihd.net/steam/apps/879930/page_bg_generated_v6b.jpg?t=1531259811",
            "content_descriptors": {
                "ids": [],
                "notes": null
            }
        }
    }
}